{"de":{"Remove":"de--Remove selected","Edit":"de--Edit","TableSelectionLabel":"de--Please choose a table to view\r\nthe following tables are lists of orders\r\npreviously created","ItemListQuantity":"de--Item Quantity","ItemListName":"de--Item Name"},"fr":{"Remove":"fr--Remove selected","Edit":"fr--Edit","TableSelectionLabel":"fr--Please choose a table to view\r\nthe following tables are lists of orders\r\npreviously created","ItemListQuantity":"fr--Item Quantity","ItemListName":"fr--Item Name"},"sv":{"Remove":"sv--Remove selected","Edit":"sv--Edit","TableSelectionLabel":"sv--Please choose a table to view\r\nthe following tables are lists of orders\r\npreviously created","ItemListQuantity":"sv--Item Quantity","ItemListName":"sv--Item Name"},"en":{"Remove":"Remove selected","Edit":"Edit","TableSelectionLabel":"Please choose a table to view\r\nthe following tables are lists of orders\r\npreviously created","ItemListQuantity":"Item Quantity","ItemListName":"Item Name"}}